verb_conjugator/__init__.py
verb_conjugator/__main__.py
verb_conjugator/data.py
verb_conjugator/verb_conjugator.py
verb_conjugator-0.0.4.dist-info/METADATA
verb_conjugator-0.0.4.dist-info/WHEEL
verb_conjugator-0.0.4.dist-info/entry_points.txt
verb_conjugator-0.0.4.dist-info/licenses/LICENSE
verb_conjugator-0.0.4.dist-info/RECORD
