Metadata-Version: 2.1
Name: verb-conjugator
Version: 0.0.4
Summary: A tool to practice verb conjugations in french and spanish
Project-URL: Homepage, https://github.com/theonlysam/verb-conjugator
Project-URL: Bug Tracker, https://github.com/theonlysam/verb-conjugator/issues
Author-email: Marc Smith <theonlymarcsmith@gmail.com>
License-File: LICENSE
Classifier: License :: OSI Approved :: MIT License
Classifier: Operating System :: OS Independent
Classifier: Programming Language :: Python :: 3
Requires-Python: >=3.6
Requires-Dist: verbecc==1.8.1
Provides-Extra: test
Requires-Dist: pytest; extra == 'test'
